Metadata-Version: 2.1
Name: movie-rec
Version: 0.0.5
Summary: Movie recomendation system
Home-page: UNKNOWN
Author: Lilith Petrosyan, Zhora Stepanyan, Petros Petrosyan, Artashes Mezhlumyan
License: UNKNOWN
Platform: UNKNOWN
